{
  "startAt": 0,
  "maxResults": 5000,
  "total": 1,
  "comments": [
    {
      "self": "https://api.atlassian.com/ex/jira/f6eef702-e05d-43ba-bd5c-75fce47d560e/rest/api/3/issue/10709/comment/10024",
      "id": "10024",
      "author": {
        "self": "https://api.atlassian.com/ex/jira/f6eef702-e05d-43ba-bd5c-75fce47d560e/rest/api/3/user?accountId=608a9b555426330072f9867d",
        "accountId": "608a9b555426330072f9867d",
        "emailAddress": "andres@worklytics.co",
        "avatarUrls": {
          "48x48": "https://secure.gravatar.com/avatar/ac6ffe47a35e01c2ae94a5672d52cfc7?d=https%3A%2F%2Favatar-management--avatars.us-west-2.prod.public.atl-paas.net%2Finitials%2FA-3.png",
          "24x24": "https://secure.gravatar.com/avatar/ac6ffe47a35e01c2ae94a5672d52cfc7?d=https%3A%2F%2Favatar-management--avatars.us-west-2.prod.public.atl-paas.net%2Finitials%2FA-3.png",
          "16x16": "https://secure.gravatar.com/avatar/ac6ffe47a35e01c2ae94a5672d52cfc7?d=https%3A%2F%2Favatar-management--avatars.us-west-2.prod.public.atl-paas.net%2Finitials%2FA-3.png",
          "32x32": "https://secure.gravatar.com/avatar/ac6ffe47a35e01c2ae94a5672d52cfc7?d=https%3A%2F%2Favatar-management--avatars.us-west-2.prod.public.atl-paas.net%2Finitials%2FA-3.png"
        },
        "displayName": "aperez",
        "active": true,
        "timeZone": "America/New_York",
        "accountType": "atlassian"
      },
      "body": {
        "version": 1,
        "type": "doc",
        "content": [
          {
            "type": "paragraph",
            "content": [
              {
                "type": "mention",
                "attrs": {
                  "id": "608a9b555426330072f9867d",
                  "text": "@aperez",
                  "accessLevel": ""
                }
              },
              {
                "type": "text",
                "text": " do it!"
              }
            ]
          }
        ]
      },
      "updateAuthor": {
        "self": "https://api.atlassian.com/ex/jira/f6eef702-e05d-43ba-bd5c-75fce47d560e/rest/api/3/user?accountId=608a9b555426330072f9867d",
        "accountId": "608a9b555426330072f9867d",
        "emailAddress": "andres@worklytics.co",
        "avatarUrls": {
          "48x48": "https://secure.gravatar.com/avatar/ac6ffe47a35e01c2ae94a5672d52cfc7?d=https%3A%2F%2Favatar-management--avatars.us-west-2.prod.public.atl-paas.net%2Finitials%2FA-3.png",
          "24x24": "https://secure.gravatar.com/avatar/ac6ffe47a35e01c2ae94a5672d52cfc7?d=https%3A%2F%2Favatar-management--avatars.us-west-2.prod.public.atl-paas.net%2Finitials%2FA-3.png",
          "16x16": "https://secure.gravatar.com/avatar/ac6ffe47a35e01c2ae94a5672d52cfc7?d=https%3A%2F%2Favatar-management--avatars.us-west-2.prod.public.atl-paas.net%2Finitials%2FA-3.png",
          "32x32": "https://secure.gravatar.com/avatar/ac6ffe47a35e01c2ae94a5672d52cfc7?d=https%3A%2F%2Favatar-management--avatars.us-west-2.prod.public.atl-paas.net%2Finitials%2FA-3.png"
        },
        "displayName": "aperez",
        "active": true,
        "timeZone": "America/New_York",
        "accountType": "atlassian"
      },
      "created": "2022-03-02T09:00:54.241-0500",
      "updated": "2022-03-02T09:00:54.241-0500",
      "jsdPublic": true
    }
  ]
}